{
  "version": "1.1.0",
  "diagrams": [
    {
      "ordinal": 0,
      "scrollPosition": {
        "x": 0,
        "y": 0
      },
      "nodes": [
        {
          "location": {
            "x": 358,
            "y": 364
          },
          "nodeIndex": "bcts_reporting vw_silviliability_main",
          "nodeLineageTag": "c61c3815-a035-413f-8d9b-866f23aae6ee",
          "size": {
            "height": 300,
            "width": 234
          },
          "zIndex": 0
        },
        {
          "location": {
            "x": 50,
            "y": -50
          },
          "nodeIndex": "bcts_reporting vw_silviliability_main_pbi",
          "nodeLineageTag": "81d49811-1289-4d5a-bc77-4d1cc63a4798",
          "size": {
            "height": 300,
            "width": 234
          },
          "zIndex": 0
        },
        {
          "location": {
            "x": 762,
            "y": 74
          },
          "nodeIndex": "bcts_staging dim_business_area",
          "nodeLineageTag": "adf6c8bd-1a02-43ff-baf6-7405d62611f0",
          "size": {
            "height": 200,
            "width": 234
          },
          "zIndex": 0
        }
      ],
      "name": "All tables",
      "zoomValue": 100,
      "pinKeyFieldsToTop": false,
      "showExtraHeaderInfo": false,
      "hideKeyFieldsWhenCollapsed": false,
      "tablesLocked": false
    }
  ],
  "selectedDiagram": "All tables",
  "defaultDiagram": "All tables"
}